src/converter/__init__.py
src/converter/blocknote_to_dict.py
src/converter/blocknote_to_html.py
src/converter/blocknote_to_md.py
src/converter/dict_to_blocknote.py
src/converter/html_to_blocknote.py
src/converter/md_to_blocknote.py
src/converter/__tests__/__init__.py
src/converter/__tests__/test_blocknote_to_dict.py
src/converter/__tests__/test_blocknote_to_html.py
src/converter/__tests__/test_blocknote_to_md.py
src/converter/__tests__/test_dict_to_blocknote.py
src/converter/__tests__/test_html_to_blocknote.py
src/converter/__tests__/test_md_to_blocknote.py
src/schema/__init__.py
src/schema/types.py
blocknote/converter/__init__.py
blocknote/converter/blocknote_to_dict.py
blocknote/converter/blocknote_to_html.py
blocknote/converter/blocknote_to_md.py
blocknote/converter/dict_to_blocknote.py
blocknote/converter/html_to_blocknote.py
blocknote/converter/md_to_blocknote.py
blocknote/converter/__tests__/__init__.py
blocknote/converter/__tests__/test_blocknote_to_dict.py
blocknote/converter/__tests__/test_blocknote_to_html.py
blocknote/converter/__tests__/test_blocknote_to_md.py
blocknote/converter/__tests__/test_dict_to_blocknote.py
blocknote/converter/__tests__/test_html_to_blocknote.py
blocknote/converter/__tests__/test_md_to_blocknote.py
blocknote/schema/__init__.py
blocknote/schema/types.py
blocknote_py-0.2.0.dist-info/METADATA
blocknote_py-0.2.0.dist-info/WHEEL
blocknote_py-0.2.0.dist-info/licenses/LICENSE
blocknote_py-0.2.0.dist-info/RECORD
