Metadata-Version: 2.4
Name: blocknote-py
Version: 0.2.0
Summary: BlockNote Python library - Official Python support for BlockNote.js. Convert BlockNote blocks to HTML, Markdown, and JSON with full type safety and validation.
Project-URL: Homepage, https://github.com/rohansharmasitoula/blocknote-py
Project-URL: Documentation, https://rohansharmasitoula.github.io/blocknote-py/
Project-URL: Repository, https://github.com/rohansharmasitoula/blocknote-py
Project-URL: Bug Tracker, https://github.com/rohansharmasitoula/blocknote-py/issues
Project-URL: Changelog, https://rohansharmasitoula.github.io/blocknote-py/changelog/
Project-URL: Funding, https://buymeacoffee.com/sitoularohansharma
Author-email: Rohan Sharma Sitoula <rohansharmasitoula@gmail.com>
Maintainer-email: Rohan Sharma Sitoula <rohansharmasitoula@gmail.com>
License: MIT License
License-File: LICENSE
Keywords: block-note-python,blocknote,blocknote-py,blocknote-python,blocks,converter,html,json,markdown,python-blocknote,rich-text
Classifier: Development Status :: 4 - Beta
Classifier: Intended Audience :: Developers
Classifier: License :: OSI Approved :: MIT License
Classifier: Operating System :: OS Independent
Classifier: Programming Language :: Python :: 3
Classifier: Programming Language :: Python :: 3.8
Classifier: Programming Language :: Python :: 3.9
Classifier: Programming Language :: Python :: 3.10
Classifier: Programming Language :: Python :: 3.11
Classifier: Programming Language :: Python :: 3.12
Classifier: Programming Language :: Python :: 3.13
Classifier: Topic :: Internet :: WWW/HTTP :: Dynamic Content
Classifier: Topic :: Software Development :: Libraries :: Python Modules
Classifier: Topic :: Text Processing :: Markup :: HTML
Classifier: Topic :: Text Processing :: Markup :: Markdown
Classifier: Typing :: Typed
Requires-Python: >=3.8
Requires-Dist: markdown-it-py>=3.0.0
Requires-Dist: pydantic>=2.0.0
Provides-Extra: all
Requires-Dist: black>=23.0.0; extra == 'all'
Requires-Dist: flake8>=5.0.0; extra == 'all'
Requires-Dist: isort>=5.12.0; extra == 'all'
Requires-Dist: mkdocs-material>=9.0.0; extra == 'all'
Requires-Dist: mkdocs>=1.5.0; extra == 'all'
Requires-Dist: mkdocstrings[python]>=0.20.0; extra == 'all'
Requires-Dist: mypy>=1.0.0; extra == 'all'
Requires-Dist: pre-commit>=3.0.0; extra == 'all'
Requires-Dist: pytest-cov>=4.1.0; extra == 'all'
Requires-Dist: pytest>=7.4.0; extra == 'all'
Provides-Extra: dev
Requires-Dist: black>=23.0.0; extra == 'dev'
Requires-Dist: flake8>=5.0.0; extra == 'dev'
Requires-Dist: isort>=5.12.0; extra == 'dev'
Requires-Dist: mypy>=1.0.0; extra == 'dev'
Requires-Dist: pre-commit>=3.0.0; extra == 'dev'
Provides-Extra: docs
Requires-Dist: mkdocs-material>=9.0.0; extra == 'docs'
Requires-Dist: mkdocs>=1.5.0; extra == 'docs'
Requires-Dist: mkdocstrings[python]>=0.20.0; extra == 'docs'
Provides-Extra: test
Requires-Dist: pytest-cov>=4.1.0; extra == 'test'
Requires-Dist: pytest>=7.4.0; extra == 'test'
